nonebot_plugin_cube/__init__.py
nonebot_plugin_cube/rank.py
nonebot_plugin_cube/render.py
nonebot_plugin_cube-1.0.8.dist-info/METADATA
nonebot_plugin_cube-1.0.8.dist-info/WHEEL
nonebot_plugin_cube-1.0.8.dist-info/RECORD
