Metadata-Version: 2.1
Name: nonebot-plugin-cube
Version: 1.0.8
Summary: Rubik's Cube plugin based on nonebot framework,基于nonebot框架的魔方插件
License: AGPL-3.0
Author: initialencounter
Author-email: 2911583893@qq.com
Requires-Python: >=3.8,<4.0
Classifier: License :: OSI Approved :: GNU Affero General Public License v3
Classifier: Programming Language :: Python :: 3
Classifier: Programming Language :: Python :: 3.8
Classifier: Programming Language :: Python :: 3.9
Classifier: Programming Language :: Python :: 3.10
Classifier: Programming Language :: Python :: 3.11
Classifier: Programming Language :: Python :: 3.12
Requires-Dist: Pillow (>=9.0.0,<10.0.0)
Requires-Dist: cube-rs (>=0.1.0,<0.2.0)
Requires-Dist: nonebot-adapter-onebot (>=2.0.0b1,<3.0.0)
Requires-Dist: nonebot2 (>=2.0.0b2,<3.0.0)
